{"cameraMode":{"drawMode":0,"name":"Shaded","section":"Shading Mode"},"sceneLighting":true,"audioPlay":false,"sceneViewState":{"m_AlwaysRefresh":false,"showFog":true,"showSkybox":true,"showFlares":true,"showImageEffects":true,"showParticleSystems":true,"showVisualEffectGraphs":true,"m_FxEnabled":true},"in2DMode":false,"pivot":{"x":1.3127087354660035,"y":2.531419277191162,"z":2.315530776977539},"rotation":{"x":-0.08796904981136322,"y":0.9116101264953613,"z":-0.2688709497451782,"w":-0.29825642704963686},"size":0.4740454852581024,"orthographic":false}